ldrpyutils/__init__.py
ldrpyutils/core.py
ldrpyutils/data/prefixes.ttl
ldrpyutils-0.2.4.dist-info/DESCRIPTION.rst
ldrpyutils-0.2.4.dist-info/METADATA
ldrpyutils-0.2.4.dist-info/RECORD
ldrpyutils-0.2.4.dist-info/WHEEL
ldrpyutils-0.2.4.dist-info/entry_points.txt
ldrpyutils-0.2.4.dist-info/metadata.json
ldrpyutils-0.2.4.dist-info/top_level.txt
